ifdef/__init__.py
ifdef/global_vars.py
ifdef/import_wrapper.py
ifdef/test/__init__.py
ifdef/test/__main__.py
ifdef/test/_test_ifdef1.py
ifdef/test/_test_ifdef2.py
ifdef/test/_test_ifdef3.py
ifdef/test/_test_ifdef4.py
ifdef/test/test_ifdef.py
ifdef-0.1.4.dist-info/licenses/LICENSE
ifdef-0.1.4.dist-info/METADATA
ifdef-0.1.4.dist-info/WHEEL
ifdef-0.1.4.dist-info/top_level.txt
ifdef-0.1.4.dist-info/RECORD
